{
  RBA: {
    bank_name: "Reserve Bank of Australia",
    bank_type: "PUBLIC SECTOR BANKS",
    bank_type_code: "RBA",
    base_url: "https://www.rba.gov.au/",
    headers: {
      "User-Agent": "Mozilla/5.0 (Windows NT 10.0; Win64; x64) AppleWebKit/537.36 (KHTML, like Gecko) Chrome/125.0.0.0 Safari/537.36",
      "Accept-Language": "en-US,en;q=0.9",
    },
    blocks: [
      "action_table",
       {
        action: "download",
        by: "css",
        value: "a.FDlink.pdf-data",
        multiple: true,
        wait_until: "clickable",
        default_wait: 5,
        timeout: 20,
        log_message: "Axis Bank",
    },
      "action_table",
    ],
    intial_window_size: [900, 700],
  },
    BCA: {
    bank_name: "Bank of Canada",
    bank_type: "PUBLIC SECTOR BANKS",
    bank_type_code: "BCA",
    base_url: "https://www.bankofcanada.ca/rates/interest-rates/canadian-interest-rates/?lookupPage=lookup_canadian_interest.php&startRange=2015-09-23&rangeType=dates&dFrom=2025-08-01&dTo=2025-09-22&rangeValue=1&rangeWeeklyValue=1&rangeMonthlyValue=1&series%5B%5D=LOOKUPS_V39079&series%5B%5D=CL.CDN.MOST.1DL&series%5B%5D=V39078&series%5B%5D=V80691310&series%5B%5D=V122530&ByDate_frequency=daily&submit_button=Submit",
    headers: {
      "User-Agent": "Mozilla/5.0 (Windows NT 10.0; Win64; x64) AppleWebKit/537.36 (KHTML, like Gecko) Chrome/125.0.0.0 Safari/537.36",
      "Accept-Language": "en-US,en;q=0.9",
    },
    blocks: [
      "action_table",
    //   {
    //     action: "website",
    //     by: "tag",
    //     value: "body",
    //     url: "https://www.bankofbaroda.in/interest-rate-and-service-charges/retail-loans-interest-rates",
    //     default_wait: 5,
    //     timeout: 20,
    //   },
    //   "action_table",
    ],
    intial_window_size: [900, 700],
  },
  BMEX: {
    bank_name: "Bank of Mexico",
    bank_type: "PUBLIC SECTOR BANKS",
    bank_type_code: "BMEX",
    base_url: "https://www.banxico.org.mx/SieInternet/",
    headers: {
      "User-Agent": "Mozilla/5.0 (Windows NT 10.0; Win64; x64) AppleWebKit/537.36 (KHTML, like Gecko) Chrome/125.0.0.0 Safari/537.36",
      "Accept-Language": "en-US,en;q=0.9",
    },
    blocks: [
      {
        action: "website",
        by: "tag",
        value: "body",
        url: "https://www.banxico.org.mx/SieInternet/consultarDirectorioInternetAction.do?accion=consultarCuadro&idCuadro=CF101&sector=18&locale=en",
        default_wait: 5,
        timeout: 20,
      },
      {
        action: "click_save",
        by: "css",
        value: "#botonExportarCuadro",
        skip_if_not_found: true,
        wait_until: "present",
        default_wait: 3,
        timeout: 15,
    },
    ],
    intial_window_size: [900, 700],
  },
  

}
